mtwpay-1.0.1.dist-info/licenses/LICENSE
mytonwallet_pay/__init__.py
mytonwallet_pay/loggers.py
mytonwallet_pay/client/__init__.py
mytonwallet_pay/client/client.py
mytonwallet_pay/client/client.pyi
mytonwallet_pay/methods/__init__.py
mytonwallet_pay/methods/base.py
mytonwallet_pay/methods/create_invoice.py
mytonwallet_pay/methods/get_invoices.py
mytonwallet_pay/methods/get_me.py
mytonwallet_pay/session/__init__.py
mytonwallet_pay/session/aiohttp.py
mytonwallet_pay/tools/__init__.py
mytonwallet_pay/tools/check_token.py
mytonwallet_pay/tools/get_invoice.py
mytonwallet_pay/types/Coin.py
mytonwallet_pay/types/Invoice.py
mytonwallet_pay/types/InvoiceStatus.py
mytonwallet_pay/types/Project.py
mytonwallet_pay/types/__init__.py
mytonwallet_pay/types/base.py
mytonwallet_pay/types/error.py
mtwpay-1.0.1.dist-info/METADATA
mtwpay-1.0.1.dist-info/WHEEL
mtwpay-1.0.1.dist-info/top_level.txt
mtwpay-1.0.1.dist-info/RECORD
