Metadata-Version: 2.4
Name: mtwpay
Version: 1.0.1
Summary: Python SDK for MyTonWallet Pay API
Author-email: LaFTon Technology <laftonsup@gmail.com>
License-Expression: MIT
Project-URL: Homepage, https://github.com/LaFTonTechnology/mytonwallet_pay
Project-URL: Repository, https://github.com/LaFTonTechnology/mytonwallet_pay
Project-URL: Issues, https://github.com/LaFTonTechnology/mytonwallet_pay/issues
Keywords: MyTonWallet,MyTonWallet Pay,MyTonWallet Pay API,MTW Pay,MTW
Requires-Python: >=3.10
License-File: LICENSE
Requires-Dist: pydantic>=2.0
Requires-Dist: certifi
Requires-Dist: aiohappyeyeballs>=2.6.1
Requires-Dist: aiohttp>=3.12.15
Requires-Dist: aiosignal>=1.4.0
Requires-Dist: annotated-types>=0.7.0
Requires-Dist: attrs>=25.3.0
Requires-Dist: frozenlist>=1.7.0
Requires-Dist: idna>=3.10
Requires-Dist: multidict>=6.6.4
Requires-Dist: propcache>=0.3.2
Requires-Dist: typing-inspection>=0.4.1
Requires-Dist: typing_extensions>=4.15.0
Requires-Dist: yarl>=1.20.1
Dynamic: license-file
